openapi_mcp/__init__.py
openapi_mcp/auth.py
openapi_mcp/config.py
openapi_mcp/exceptions.py
openapi_mcp/fastmcp_server.py
openapi_mcp/mcp_transport.py
openapi_mcp/openapi_loader.py
openapi_mcp/request_handler.py
openapi_mcp/schema_converter.py
openapi_mcp/server.py
openapi_mcp/sse_handler.py
openapi_mcp/sse_server.py
openapi_mcp/tool_factory.py
openapi_mcp/types.py
openapi_mcp_proxy-1.0.4.dist-info/licenses/LICENSE
openapi_mcp_proxy-1.0.4.dist-info/METADATA
openapi_mcp_proxy-1.0.4.dist-info/WHEEL
openapi_mcp_proxy-1.0.4.dist-info/entry_points.txt
openapi_mcp_proxy-1.0.4.dist-info/top_level.txt
openapi_mcp_proxy-1.0.4.dist-info/RECORD
