Metadata-Version: 2.4
Name: openapi-mcp-proxy
Version: 1.0.4
Summary: OpenAPI to Model Context Protocol (MCP) proxy server - dynamically translates OpenAPI specs into MCP tools
Author-email: Roger Gujord <roger@gujord.no>
License: MIT
Project-URL: Homepage, https://github.com/gujord/OpenAPI-MCP
Project-URL: Repository, https://github.com/gujord/OpenAPI-MCP
Project-URL: Documentation, https://github.com/gujord/OpenAPI-MCP#readme
Project-URL: Issues, https://github.com/gujord/OpenAPI-MCP/issues
Keywords: mcp,openapi,model-context-protocol,ai,llm,api,proxy,fastmcp,claude
Classifier: Development Status :: 4 - Beta
Classifier: Intended Audience :: Developers
Classifier: License :: OSI Approved :: MIT License
Classifier: Operating System :: OS Independent
Classifier: Programming Language :: Python :: 3
Classifier: Programming Language :: Python :: 3.10
Classifier: Programming Language :: Python :: 3.11
Classifier: Programming Language :: Python :: 3.12
Classifier: Topic :: Software Development :: Libraries :: Python Modules
Classifier: Topic :: Internet :: WWW/HTTP
Requires-Python: >=3.10
License-File: LICENSE
Requires-Dist: annotated-types>=0.7.0
Requires-Dist: anyio>=4.9.0
Requires-Dist: certifi>=2025.1.31
Requires-Dist: click>=8.1.8
Requires-Dist: h11>=0.16.0
Requires-Dist: httpcore>=1.0.9
Requires-Dist: httpx>=0.28.1
Requires-Dist: httpx-sse>=0.4.0
Requires-Dist: idna>=3.10
Requires-Dist: mcp>=1.23.0
Requires-Dist: fastmcp>=2.13.0
Requires-Dist: pydantic>=2.10.6
Requires-Dist: pydantic-settings>=2.8.1
Requires-Dist: python-dotenv>=1.0.1
Requires-Dist: PyYAML>=6.0.2
Requires-Dist: sniffio>=1.3.1
Requires-Dist: sse-starlette>=2.2.1
Requires-Dist: starlette>=0.46.1
Requires-Dist: typing_extensions>=4.12.2
Requires-Dist: uvicorn>=0.34.0
Provides-Extra: dev
Requires-Dist: pytest>=7.0.0; extra == "dev"
Requires-Dist: pytest-asyncio>=0.21.0; extra == "dev"
Requires-Dist: pytest-cov>=4.0.0; extra == "dev"
Dynamic: license-file
